datalaboauthenticator/__init__.py
datalaboauthenticator/datalab.py
jupyterhub_datalaboauthenticator-1.0.dist-info/LICENSE
jupyterhub_datalaboauthenticator-1.0.dist-info/METADATA
jupyterhub_datalaboauthenticator-1.0.dist-info/WHEEL
jupyterhub_datalaboauthenticator-1.0.dist-info/entry_points.txt
jupyterhub_datalaboauthenticator-1.0.dist-info/top_level.txt
jupyterhub_datalaboauthenticator-1.0.dist-info/RECORD
