Metadata-Version: 2.1
Name: jupyterhub-datalaboauthenticator
Version: 1.0
Summary: Custom OAuthenticator for the Datalab
Home-page: https://github.com/aidaph/datalaboauthenticator
Author: Aida Palacio
Author-email: aidaph@ifca.unican.es
License: UNKNOWN
Platform: UNKNOWN
Requires-Python: >=3.8
License-File: LICENSE
